AUTHORS
LICENSE
README.md
setup.py
./oidc_provider/__init__.py
./oidc_provider/admin.py
./oidc_provider/application.py
./oidc_provider/apps.py
./oidc_provider/decorators.py
./oidc_provider/exceptions.py
./oidc_provider/models.py
./oidc_provider/urls.py
./oidc_provider/users.py
./oidc_provider/utils.py
./oidc_provider/views.py
./oidc_provider/__pycache__/__init__.cpython-38.pyc
./oidc_provider/__pycache__/admin.cpython-38.pyc
./oidc_provider/__pycache__/application.cpython-38.pyc
./oidc_provider/__pycache__/apps.cpython-38.pyc
./oidc_provider/__pycache__/configure.cpython-38.pyc
./oidc_provider/__pycache__/db_interfaces.cpython-38.pyc
./oidc_provider/__pycache__/decorators.cpython-38.pyc
./oidc_provider/__pycache__/exceptions.cpython-38.pyc
./oidc_provider/__pycache__/models.cpython-38.pyc
./oidc_provider/__pycache__/urls.cpython-38.pyc
./oidc_provider/__pycache__/users.cpython-38.pyc
./oidc_provider/__pycache__/utils.cpython-38.pyc
./oidc_provider/__pycache__/views.cpython-38.pyc
./oidc_provider/migrations/0001_initial.py
./oidc_provider/migrations/0002_oidcsession_salt.py
./oidc_provider/migrations/0003_auto_20210510_1353.py
./oidc_provider/migrations/0004_auto_20210511_0940.py
./oidc_provider/migrations/0005_oidcsession_sid_encrypted.py
./oidc_provider/migrations/0006_auto_20210515_1001.py
./oidc_provider/migrations/0007_auto_20210516_1230.py
./oidc_provider/migrations/0008_auto_20210516_1653.py
./oidc_provider/migrations/0009_auto_20210517_1803.py
./oidc_provider/migrations/0010_remove_oidcsession_session_info.py
./oidc_provider/migrations/0011_auto_20210608_1705.py
./oidc_provider/migrations/__init__.py
./oidc_provider/migrations/__pycache__/0001_initial.cpython-38.pyc
./oidc_provider/migrations/__pycache__/0002_auto_20191204_1349.cpython-38.pyc
./oidc_provider/migrations/__pycache__/0002_auto_20210310_1830.cpython-38.pyc
./oidc_provider/migrations/__pycache__/0002_auto_20210510_0946.cpython-38.pyc
oidc_provider.egg-info/PKG-INFO
oidc_provider.egg-info/SOURCES.txt
oidc_provider.egg-info/dependency_links.txt
oidc_provider.egg-info/not-zip-safe
oidc_provider.egg-info/requires.txt
oidc_provider.egg-info/top_level.txt