Metadata-Version: 2.1
Name: oidc-provider
Version: 2.3.4
Summary: django oidc provider
Home-page: https://github.com/peppelinux/django-oidc-op
Author: Giuseppe De Marco
Author-email: demarcog83@gmail.com
License: Apache 2.0
Platform: UNKNOWN
Classifier: Development Status :: 5 - Production/Stable
Classifier: License :: OSI Approved :: Apache Software License
Classifier: Programming Language :: Python :: 3.6
Classifier: Programming Language :: Python :: 3.7
Classifier: Programming Language :: Python :: 3.8
Classifier: Topic :: Software Development :: Libraries :: Python Modules
License-File: LICENSE
License-File: AUTHORS
